prodpy/__init__.py
prodpy/_allocate.py
prodpy/_decline.py
prodpy/_schedule.py
prodpy/_timespan.py
prodpy/decline/__init__.py
prodpy/decline/_analysis.py
prodpy/decline/_arps.py
prodpy/decline/_arpsmodel.py
prodpy/decline/_dcanalysis.py
prodpy/decline/_exponential.py
prodpy/decline/_harmonic.py
prodpy/decline/_hyperbolic.py
prodpy/onepage/__init__.py
prodpy/onepage/_annual_production.py
prodpy/onepage/_bubble_map_circles.py
prodpy/onepage/_bubble_map_pie_chart.py
prodpy/onepage/_charts.py
prodpy/onepage/_forecast.py
prodpy/onepage/_history.py
prodpy/onepage/_production_vstime.py
prodpy/onepage/_spatial.py
prodpy/onepage/_templix.py
prodpy/onepage/_tornado_chart.py
prodpy/onepage/_waterfall_chart.py
prodpy/onepage/_well_status_pie_chart.py
prodpy/stream/__init__.py
prodpy/stream/_perforation_vstime.py
prodpy/stream/_production_vstime.py
prodpy-0.0.29.dist-info/METADATA
prodpy-0.0.29.dist-info/WHEEL
prodpy-0.0.29.dist-info/top_level.txt
prodpy-0.0.29.dist-info/RECORD
