Metadata-Version: 2.1
Name: prodpy
Version: 0.0.29
Summary: Production forecasting utilities and decline-curve analysis tools built around Arps models.
Author: Javid Shiriyev
Project-URL: Homepage, https://github.com/jshiriyev/data-driven-forecasting
Project-URL: Documentation, https://github.com/jshiriyev/data-driven-forecasting/tree/main/docs
Project-URL: Issues, https://github.com/jshiriyev/data-driven-forecasting/issues
Project-URL: Changelog, https://github.com/jshiriyev/data-driven-forecasting/releases
Keywords: petroleum engineering,decline-curve,arps,production forecasting
Classifier: Development Status :: 3 - Alpha
Classifier: Intended Audience :: Science/Research
Classifier: Intended Audience :: Manufacturing
Classifier: Topic :: Scientific/Engineering
Classifier: Programming Language :: Python :: 3
Classifier: Programming Language :: Python :: 3.10
Classifier: Programming Language :: Python :: 3.11
Classifier: Programming Language :: Python :: 3.12
Classifier: Operating System :: OS Independent
Classifier: Natural Language :: English
Requires-Python: >=3.10
Requires-Dist: numpy >=1.26.4
Requires-Dist: openpyxl >=3.1.2
Requires-Dist: pandas >=2.2.2
Requires-Dist: scipy >=1.13.0
